kameleoon_openfeature/__init__.py
kameleoon_openfeature/data_converter.py
kameleoon_openfeature/kameleoon_provider.py
kameleoon_openfeature/resolver.py
kameleoon_openfeature/sdk_version.py
kameleoon_openfeature/types.py
kameleoon_openfeature-0.0.1.dist-info/METADATA
kameleoon_openfeature-0.0.1.dist-info/WHEEL
kameleoon_openfeature-0.0.1.dist-info/top_level.txt
kameleoon_openfeature-0.0.1.dist-info/RECORD
