Metadata-Version: 2.1
Name: kameleoon-openfeature
Version: 0.0.1
Summary: OpenFeature Kameleoon Provider.
Home-page: https://developers.kameleoon.com/python-sdk.html
Author: Kameleoon
Author-email: sdk@kameleoon.com
License: GPLv3
Platform: UNKNOWN
Classifier: License :: OSI Approved :: GNU General Public License v3 (GPLv3)
Classifier: Programming Language :: Python
Classifier: Programming Language :: Python :: 3.8
Classifier: Programming Language :: Python :: 3.9
Classifier: Programming Language :: Python :: 3.10
Classifier: Programming Language :: Python :: Implementation :: CPython
Classifier: Programming Language :: Python :: Implementation :: PyPy
Requires-Python: >=3.8.0
Requires-Dist: openfeature-sdk>=0.7.1
Requires-Dist: kameleoon-client-python>=3.3.3
Provides-Extra: test
Requires-Dist: flake8==7.1.1; extra == "test"
Requires-Dist: openfeature-sdk>=0.7.1; extra == "test"
Requires-Dist: pylint==3.2.7; extra == "test"
Requires-Dist: kameleoon-client-python>=3.3.3; extra == "test"
Requires-Dist: mypy==1.11.2; extra == "test"
Requires-Dist: pytest==8.3.3; extra == "test"
